[
    {
        "list": [
            132
        ],
        "months": [
            "2018-05"
        ],
        "ne": [
            "Arkansas",
            "Trump",
            "India",
            "South Carolina",
            "Immigration Skirmish Reveals",
            "Texas Once",
            "Trump Congress",
            "Word And Deed",
            "Paul Ryan",
            "Latina",
            "Experimental Drugs",
            "Abrams",
            "CFPB",
            "FDA",
            "Bill Clinton Five",
            "Easier Access",
            "Kentucky House",
            "Sexual Harassment Legislation Congress To Undo Part Of Dodd-Frank",
            "Texas Dem",
            "Hogan",
            "Kemp",
            "Unproven Drugs House",
            "Experimental Drugs Congress",
            "Cuomo Dear",
            "Kentucky",
            "Southern",
            "AUMF",
            "Surge",
            "Congress Trump",
            "Texas",
            "Bernie Sanders",
            "McCarthy",
            "Campaign",
            "Angry",
            "Join",
            "America Mick Mulvaney",
            "GOP",
            "Warren Freedom Caucus",
            "Stacey Abrams",
            "California",
            "Ryan",
            "Banana States",
            "Ryan Urges Unity",
            "Trump Era Election",
            "Midterms",
            "WATCH",
            "House Dem",
            "Trump Rallies Abortion Rights Opponents",
            "Women Running",
            "McConnell Plot Path",
            "Texas Runoff Election",
            "Georgia",
            "Russian",
            "Dems",
            "Georgia Trump",
            "Easing Rules For Midsize",
            "Texas No Dems",
            "Classroom Walkouts",
            "House Approves Giving Terminally Ill Quicker Access",
            "New Role",
            "Trump Reuters",
            "Trump House",
            "Tennessee",
            "Biggest",
            "White House Kentucky",
            "Democrat Beto",
            "U.S. House",
            "Swamp",
            "Cavuto Spars",
            "Next",
            "Cash Trump",
            "Senate Democrats",
            "Life Gala Kentucky Election",
            "Tonight",
            "Midterm Election",
            "Stacey Evans",
            "McEnany",
            "Smaller Banks Georgia",
            "Texas Senate",
            "Cynthia Nixon",
            "Hill",
            "Democratic Georgia",
            "Cuomo Democrats Target Trump",
            "Senate Finance Committee",
            "Trump Officials Assure",
            "DHS",
            "Democratic Party",
            "Beltway",
            "WV",
            "Texas Georgia",
            "Odds",
            "House",
            "Iraq",
            "White House",
            "House Democrats",
            "GOP Democrats",
            "NY Gov",
            "Congress Approves Bill Giving",
            "Congress Senators Reach Tentative Deal",
            "House Ted Cruz",
            "Ballot"
        ],
        "peaks": [],
        "theme": [
            "Trump",
            "House",
            "Democrats",
            "Primary",
            "GOP",
            "Georgia",
            "Bill"
        ],
        "timestamp": "2018-05-23 04:11:02.393706-04:00",
        "toparticles": [
            [
                {
                    "_id": "5b048527421aa9476b506199",
                    "date_month": "2018-05",
                    "image": "http://a57.foxnews.com/media2.foxnews.com/BrightCove/694940094001/2018/05/22/0/0/694940094001_5788138227001_5788130613001-vs.jpg?ve=1",
                    "origin": "Fox News Politics",
                    "title": "Georgia's disappointing Democrats",
                    "ts": 1527020975,
                    "twitterid": 999024494424526850,
                    "url": "http://www.foxnews.com/politics/2018/05/22/georgias-disappointing-democrats.html"
                },
                {
                    "_id": "5b049344421aa947bb51c297",
                    "date_month": "2018-05",
                    "image": "http://thehill.com/sites/default/files/collinsdoug_042518gn_lead.jpg",
                    "origin": "The Hill",
                    "title": "House easily passes prison reform bill backed by Trump",
                    "ts": 1527026121,
                    "twitterid": 999046079885860871,
                    "url": "http://thehill.com/homenews/house/388888-house-easily-passes-prison-reform-bill-backed-by-trump?__twitter_impression=true"
                },
                {
                    "_id": "5b049344421aa947bb51c2a5",
                    "date_month": "2018-05",
                    "image": "http://thehill.com/sites/default/files/hensarlingjeb_071217kc_lead.jpg",
                    "origin": "The Hill",
                    "title": "House votes to ease regulation of banks, sending bill to Trump",
                    "ts": 1527025599,
                    "twitterid": 999043891826450432,
                    "url": "http://thehill.com/policy/finance/388839-house-votes-to-ease-regulation-of-banks-sending-bill-to-trump"
                },
                {
                    "_id": "5b04af5d421aa9489883f1b4",
                    "date_month": "2018-05",
                    "image": "https://cdn.cnn.com/cnnnext/dam/assets/170420230817-trump-dodd-frank-super-tease.jpg",
                    "origin": "CNN Politics",
                    "title": "House sends bill loosening banking regulations to Trump's desk",
                    "ts": 1527030902,
                    "twitterid": 999066134941962250,
                    "url": "https://www.cnn.com/2018/05/22/politics/house-banking-bill-vote-dodd-frank/index.html?sr=twCNNp052218house-banking-bill-vote-dodd-frank0548PMStory&CNNPolitics=Tw"
                },
                {
                    "_id": "5b04a13f421aa94820c01b1c",
                    "date_month": "2018-05",
                    "image": "https://static.politico.com/c0/db/2c72b8194426a858e6bff0b3e797/20161025-capitol-dome-191.jpg",
                    "origin": "POLITICO",
                    "title": "House sends major bank bill to Trump, capping years of effort",
                    "ts": 1527027455,
                    "twitterid": 999051676869976064,
                    "url": "https://www.politico.com/story/2018/05/22/bank-deregulation-dodd-frank-603388"
                }
            ]
        ]
    },
    {
        "list": [
            776
        ],
        "months": [
            "2018-05"
        ],
        "ne": [
            "Trump",
            "Goldman Sachs",
            "Mueller",
            "India",
            "Vito Capizzo",
            "Napa",
            "Damaged",
            "Debts Owed",
            "MCAS",
            "Point",
            "FDA",
            "Trump Prohibits Purchase",
            "Wrath Threatens Power Plant",
            "Mahathir Races",
            "IDF Over Syria Bob Corker",
            "Modern",
            "Susan",
            "Ireland",
            "Disagrees Facial",
            "Kilauea",
            "CDC",
            "Afghan Minerals",
            "Rare Bipartisan Deal U.S.",
            "American Idol",
            "EU Hunts",
            "Michael Avenatti Hit",
            "Australia Soccer",
            "Mueller Targeted Flows",
            "Israeli",
            "Iran Artist Robert Indiana",
            "Sinkhole",
            "Supreme Court",
            "Panhandle",
            "Fuel Prices",
            "Washington",
            "Bitcoin Has Boston",
            "Gina Haspel",
            "Nipah",
            "Iran Being",
            "Sanction Power",
            "Summa Cum Laude",
            "Eat Candy",
            "American Life",
            "U.S. Sanctions Five Iranians",
            "Dovey Johnson Roundtree",
            "CEO Mark Zuckerberg",
            "GOP",
            "Navy Michael Cohen",
            "France",
            "California",
            "Santa Fe",
            "Doubts Surface",
            "Malaysia",
            "Feinstein",
            "Marrakesh",
            "ADHD",
            "Chinese",
            "Mongolia",
            "Skyline Trump",
            "Economic News",
            "Utah",
            "McCain",
            "WikiLeaks",
            "Senate Continues Work Consumer Product Safety Commission Nomination",
            "Tesla",
            "New Jersey Heading",
            "Bob Ross",
            "American Novelist",
            "Betsy",
            "Swedes",
            "Zlatan Ibrahimovic",
            "Bush",
            "Reviews Grant Program",
            "Trump Approves New Sanctions",
            "Virgin Mary",
            "Who",
            "Honduran Rain Forest",
            "Wynton Marsalis",
            "TB12",
            "Yale",
            "Market Basket",
            "Expert",
            "Parliament",
            "LGBT",
            "PhRMA",
            "Herndon Monument",
            "China Nabs Suspects Using Facial Recognition Ariana Grande",
            "Yemen Australian",
            "Little League",
            "Brakes",
            "Schools",
            "House Meets Morning Hour",
            "Sign Nuclear Bailout Bill How Congress",
            "Australian Archbishop",
            "Environmental",
            "Dick",
            "Swedish Person",
            "Cohen",
            "South Korea",
            "United States",
            "PBS",
            "Toxic",
            "Hawaii Review",
            "Victoria Advocate",
            "Duchess Meghan",
            "Bloomberg",
            "European Parliament",
            "Italian Problem",
            "TX Shooting",
            "Parliament Donald Glover",
            "Anonymous",
            "Israel",
            "Captured",
            "Hawaii",
            "Meghan",
            "Alphabet",
            "Baltimore County Officer",
            "Tom Wolfe",
            "Children Are",
            "Kellogg",
            "Disneyland",
            "Fannie",
            "ISIS",
            "WNBA",
            "Carnival Cruise",
            "Life Gala The Supreme Court",
            "Roger Ailes",
            "Reddit",
            "ATF",
            "Patriots",
            "China Blames Australia",
            "Watch SpaceX",
            "Donald Glover",
            "Digital Era",
            "Honor",
            "Newton Buy Stocks",
            "David Tepper Europe",
            "Silence Him Amazon",
            "Danny Etling",
            "Manhunt",
            "Publix",
            "Boy Scouts",
            "Lando Calrissian",
            "Facebook",
            "Stormy Daniels",
            "Gun Safety",
            "Rubio",
            "Bait",
            "Religion News Service Barbara Underwood Is Named New York",
            "Get On",
            "Pacific",
            "Parkland",
            "Brett Favre",
            "Boston Globe",
            "North Korea Summit",
            "Tribeca",
            "Celebrated Novelist Philip Roth",
            "New Rocket Studied",
            "Houston Chronicle Teen",
            "Hardest Hotel Customers",
            "Baby Bonuses Grow",
            "Border Patrol",
            "ABC News",
            "Amazon",
            "Middle",
            "Zuckerberg Testifies",
            "Manchester Cathedral Helmet",
            "Formula",
            "Friends",
            "Latest News",
            "Former Bush",
            "NATO",
            "Arrested Saudi",
            "Toys",
            "High Court Teenager",
            "Meet Him",
            "Old Law Firm Hit",
            "Air Force",
            "FBI",
            "Fourth Estate",
            "Tech Vision",
            "Avert Deeper U.S.",
            "Law Firm Dispute Macron",
            "Barnier Trolls Boris Johnson",
            "Strangest Opera House",
            "Oliver North",
            "Lawsuit Taliban",
            "Business",
            "Will Be",
            "Trade",
            "FCC",
            "Auburn",
            "OTAs Amid Lawsuits And Circling Feds",
            "Josh Norman",
            "IHOP",
            "EPA",
            "Brandi Chastain",
            "Stoneman Douglas High School Therapy For Torture Victims Has Surprising Economic Benefit",
            "Iraq Colorado",
            "Retreat From Democracy Dad",
            "WATCH",
            "Vegas",
            "Brooklyn Students",
            "New Yorker Subscription Dolce",
            "Search",
            "Megyn Kelly",
            "Venezuela Mueller",
            "Florida Dimitrios Pagourtzis",
            "Shigetaka Kurita",
            "Almost No One",
            "Chesapeake",
            "Missouri",
            "Geothermal",
            "Weekly",
            "Tale",
            "Calls For Resignation Over Alleged Sexual Abuse By Gynecologist",
            "Netflix U.S",
            "Chicago HQ",
            "Really",
            "Chino Hills",
            "Map",
            "Santa Fe High",
            "Gun Violence",
            "U.S. Sanctions Iranians",
            "Taco Bell",
            "Rachel Cusk",
            "Oklahoma",
            "New Jersey",
            "Census Bureau",
            "Congress",
            "Jackson",
            "Delaying",
            "Nathan Carman",
            "Bill Cosby",
            "Crossword",
            "Mark Zuckerberg Speaks To European Union Parliament Boris Johnson Says Carney",
            "Fidelity",
            "Paul Manafort",
            "PM May",
            "Heroic",
            "Baboon",
            "England",
            "WWII Veteran",
            "How Iran Can Evade Sanctions",
            "Pentagon",
            "Backlash Ebola",
            "Commode",
            "Zuckerberg Annoys",
            "Nigel Farage",
            "Saudi Arabia",
            "Bob Corker",
            "Black Jeopardy",
            "Len Bias",
            "Deripaska",
            "Mexican Election Coverage Blockchain",
            "Speaker",
            "Penney Drops",
            "Death",
            "Obamacare",
            "Virginia Walmart",
            "Netflix Trump",
            "Jared Kushner",
            "NRA Boris Johnson",
            "Denmark",
            "Maryland",
            "Jemele Hill",
            "New York Times",
            "Airbus",
            "Miami",
            "Industry Western Mass",
            "Amid Lawsuits And Circling Feds",
            "Mute Feature Brandi Chastain",
            "Facial Recognition Fans",
            "Dave Grohl",
            "Pop Star",
            "Trump Veteran",
            "Brennan",
            "PDVSA",
            "Louisiana",
            "ICE",
            "Scheme To Silence Him Deep",
            "LIVE",
            "Venezuela Expels Top U.S.",
            "White House",
            "Baltimore County",
            "MarkZuckerberg",
            "Congo",
            "Amazon Prime",
            "Abbott",
            "Thomas Homan Testifies Immigration",
            "Brazil",
            "Jerry Richardson",
            "Beck Avenue Elizabeth Warren",
            "Dianne Feinstein",
            "Clear Pay Teachers",
            "Kansas",
            "Maddie Poppe",
            "WhiteHouse",
            "Memorial",
            "Dukha Reindeer Herders",
            "Tropical",
            "New Squeeze",
            "Iowa",
            "Yosemite",
            "Sussex",
            "West Africa Philip Roth",
            "Hate Cops",
            "Nicaraguan",
            "Hispanic",
            "Climate Change Is Real",
            "Dan Shaughessy",
            "Media",
            "South Carolina",
            "Paul Simon",
            "Boss",
            "Mexican",
            "Billboard Awards Obamas",
            "Walsh",
            "Gabbana",
            "Sweden",
            "Barack Obama",
            "Workers Stay",
            "NJ",
            "Tricky Task",
            "LeBron James",
            "Paul Bettany Sell",
            "Panama City",
            "Steve Mnuchin",
            "Susan Sarandon",
            "Dawnta Harris",
            "Donald Trump",
            "Molly Shannon",
            "ZTE",
            "Islamic State Make Millions",
            "Blasio",
            "Oregon Wildfire",
            "Second Wanted Man",
            "Crusade",
            "Mr. Rogers",
            "Massport",
            "Campaign",
            "Public Art Soars High",
            "Boris Johnson",
            "Bill Belichick",
            "Wiz",
            "City Council",
            "Naval Academy",
            "USA Gymnastics",
            "NYSE CEO",
            "Giuliani",
            "Author Of 'Portnoy",
            "Doral Trump",
            "Study Says",
            "Sessions",
            "Australia Archbishop",
            "Russians",
            "Sheriff Says",
            "Money Flows",
            "NYC Mayor",
            "Adam Rippon",
            "Uninsured Rate Held Steady",
            "Libertarian Party",
            "Army Reserve",
            "Trump Maine",
            "Canada",
            "Caleb Lee Hutchinson Uninsured",
            "Anguish",
            "Elliott Broidy",
            "Clean Drinking Water Is",
            "Long Fight Jimmy",
            "NFL",
            "Stars",
            "US Southwest Former Houston Texans",
            "Pawn",
            "New Intel Chip Flaws",
            "Please Woman",
            "ATM",
            "Father",
            "Anthem",
            "Welcome",
            "Vicodin",
            "CIA",
            "Israel Hero",
            "Montana Texas",
            "Temer Backs Former Finance Chief",
            "Mark Carney",
            "Cell From Jail",
            "New Starbucks",
            "Swamp",
            "China Mulls",
            "Abortion",
            "Danica Patrick",
            "Zakim",
            "Philip Roth",
            "AJC Cartoonist Mike Luckovich",
            "American",
            "Roger Ailes An Immigration Debate Distinct From Economic",
            "Cash Trump",
            "SWAT Team",
            "America Boris Johnson Warns",
            "ACLU",
            "Atlantic",
            "Wars VR",
            "Murphy Spending Plan Pope Francis",
            "Sanctions Retaliation Santa Fe High",
            "McDonald",
            "Balance Experimental Ebola",
            "Omni",
            "Carter Page",
            "Prince Harry",
            "MLS",
            "Galvin",
            "Yemeni Rebels",
            "Ruth Bader Ginsburg",
            "Mike Pompeo",
            "George Hill",
            "Vladimir Putin",
            "Lowe",
            "Ohio",
            "Sarah Summers",
            "NRATV",
            "Moon",
            "Noble Lynxes Square Off",
            "Chili",
            "Meghan Markle",
            "World News",
            "Netflix",
            "Eric Greitens",
            "Roman Abramovich",
            "NASCAR Champion Truex Jr Bratz",
            "Chinese Tech Unicorns Try",
            "Eggs",
            "Miss America",
            "Vicente Fox Discusses Mexico Relations",
            "Dog",
            "Miss Nebraska",
            "South",
            "Marcus Smart",
            "Andy Warhol",
            "Clinton",
            "Vacation Hot Spots Sparks Global Backlash",
            "America",
            "Cavs",
            "Treasury",
            "Japan",
            "HHS",
            "Half Dome",
            "Ariana Grande",
            "Aside",
            "Tonya Harding",
            "USC Faces Lawsuits",
            "Mark Zuckerberg",
            "Salvadoran Woman",
            "AP",
            "Brexit Bulletin",
            "Venezuela Sanctions",
            "Videos Barack",
            "Boy Scout",
            "Michelle Obama",
            "Houston Chronicle Texas",
            "Outsider",
            "Lego",
            "Massachusetts Senate",
            "Phoenix",
            "Opioid",
            "Lonely Cause Calpers",
            "Religious Freedom Restoration",
            "Eagles",
            "ICC",
            "Spanish",
            "Facebook Messenger",
            "USA",
            "Birth Controls Israel Says",
            "Political Advertising How",
            "Colleague Cryptocurrencies",
            "Strained Relations",
            "U.S.",
            "eBay",
            "Facebook Eagle",
            "Trump At",
            "Manhattan Facebook",
            "Jeep",
            "Book Review",
            "Jennifer Connelly",
            "Ugliest Aspects",
            "Kim Davis",
            "Nantucket High",
            "Refusal Trump",
            "New York",
            "Trendy",
            "Virginia Manafort",
            "Gun Control",
            "NYSE Brexit Bulletin",
            "Rob Gronkowski",
            "Brussels Too",
            "Courage Los Angeles",
            "Spotlight",
            "Legacy Fuels Bloody Conflicts",
            "Sell Brexit Britain",
            "ICA South Africa",
            "Congo How",
            "Bank",
            "Kyle Korver",
            "Hanging Rock",
            "Billboard Music Icon Award",
            "Parenthood",
            "Taxi Partner Plea Deal",
            "Goods",
            "Locals",
            "Treasury Department",
            "St. Paul",
            "Trayvon",
            "Ruin People",
            "Nassar",
            "New Money Maker",
            "Celtics Dana Loesch",
            "Pulitzer",
            "Brazil Truck Drivers Strike",
            "Provincetown",
            "Wall Street Journal",
            "New Yorker Movie Club Qaddafi Regime",
            "San Antonio",
            "Seaport Hotel",
            "Netflix Chiklis",
            "Michael Avenatti",
            "Russia Says Syria Rejects New Constitution Diluting Assad Powers",
            "Taxi Partner Enters Plea Deal",
            "Robert Indiana",
            "Former Harvard",
            "Matt Bevin",
            "Makes Unusual Pitch",
            "American Novelist Philip Roth",
            "Life Gala",
            "Escaped South Carolina Inmate Intensifies",
            "EU Say Plane",
            "Steve Bannon",
            "Europe How Europe",
            "Public Opinion Van Jones",
            "EMP",
            "Den",
            "Oregon",
            "Hurricane Harvey",
            "West Hollywood",
            "Stephen King",
            "Maserati",
            "Will See",
            "Blake Farenthold",
            "D.C.",
            "San Francisco",
            "Capitol Hill",
            "Online Political Ad Disclosure Venezuelan",
            "Brown University",
            "Kennebunkport",
            "Deliver Brexit Celtics",
            "Great Recession Venezuela",
            "Houthis Giant",
            "Source Says",
            "US",
            "Aaron Rodgers",
            "Likely",
            "Japanese",
            "French Open",
            "Uneducated",
            "Fragility Remains Kilauea",
            "Gisele Bundchen",
            "Asylum Crackdown Overdoses",
            "Wendy",
            "Pakistani",
            "Italy",
            "Nevada",
            "Show Thyself Things",
            "Joshua Schulte",
            "MH370",
            "Europe",
            "Charlottesville U.S.",
            "Elon Musk",
            "Ida",
            "Financial",
            "Carolina Panthers",
            "Basically Anyone But Her Facebook",
            "California Assad",
            "Tom Brady",
            "Whole Foods",
            "Fame Plaque Looks",
            "CBS News",
            "European",
            "Texas Gov",
            "Investment Reviews Weymouth",
            "NBC News",
            "Serena Williams",
            "Auditor",
            "Afghanistan",
            "Annual Campaign",
            "Google",
            "Freddie Artist Robert Indiana",
            "Obamas",
            "Legislature Missing",
            "Japan Ministry Releases Scandal",
            "Weinstein",
            "Brighter Economic Prospects",
            "USS Fitzgerald",
            "Vaccination Campaign Begins Jordan Peterson",
            "Exit Largest U.S.",
            "Kayaker",
            "Modena",
            "Scott Pruitt"
        ],
        "peaks": [],
        "theme": [
            "Trump",
            "Says",
            "New",
            "school",
            "year",
            "officer"
        ],
        "timestamp": "2018-05-23 04:11:11.108222-04:00",
        "toparticles": [
            [
                {
                    "_id": "5b03ea52421aa941f3de5ddb",
                    "date_month": "2018-05",
                    "image": "https://www.bostonglobe.com/rf/image_585w/Boston/2011-2020/2018/05/22/BostonGlobe.com/Metro/Images/463de47d62b04f34a720037106114f7e-463de47d62b04f34a720037106114f7e-0-JNBX.jpg",
                    "origin": "The Boston Globe",
                    "title": "Head of St. Paul\u2019s School to step down one year early after new lawsuit filed against school",
                    "ts": 1526982365,
                    "twitterid": 998862554020622336,
                    "url": "http://www.bostonglobe.com/metro/2018/05/21/head-paul-school-step-down-one-year-early-after-new-lawsuit-filed-against-school/ntRANzdsEc07MoVAwHTFRN/story.html?s_campaign=bostonglobe%3Asocialflow%3Atwitter"
                },
                {
                    "_id": "5b05119b421aa9532eaca48b",
                    "date_month": "2018-05",
                    "image": "https://cbsnews3.cbsistatic.com/hub/i/r/2018/05/22/4dfc047e-cb63-48cb-9a39-d74d76015846/thumbnail/1200x630/ed3d22274fb1726f96f62ccac71d7874/baco.jpg",
                    "origin": "CBS News",
                    "title": "16-year-old arrested, 3 others in custody after slaying of Md. officer",
                    "ts": 1527056284,
                    "twitterid": 999172591502942208,
                    "url": "https://www.cbsnews.com/news/perry-hall-baltimore-maryland-police-officer-killed-amy-caprio-4-arrests-today-2018-05-22/?ftag=COS-05-10aaa0g&utm_campaign=trueAnthem:+Trending+Content&utm_content=5b05079904d301046e90ef0c&utm_medium=trueAnthem&utm_source=twitter"
                },
                {
                    "_id": "5b044cf5421aa945eda06374",
                    "date_month": "2018-05",
                    "image": "http://thehill.com/sites/default/files/donaldtrump_05182018.jpg",
                    "origin": "The Hill",
                    "title": "Uninsured rate mostly unchanged in Trump's first year",
                    "ts": 1527007390,
                    "twitterid": 998967517157654528,
                    "url": "http://thehill.com/policy/healthcare/health-insurance/388796-uninsured-rate-stays-constant-in-trumps-first-year"
                },
                {
                    "_id": "5b044cf5421aa945eda0636e",
                    "date_month": "2018-05",
                    "image": "https://media.npr.org/assets/img/2018/05/22/ap_18141620432467_wide-bba32a0c066b4a824499732e4e9d13f7ee26dd15.jpg?s=1400",
                    "origin": "NPR Politics",
                    "title": "President Trump Approves New Sanctions On Venezuela",
                    "ts": 1527007500,
                    "twitterid": 998967978178719745,
                    "url": "https://www.npr.org/sections/thetwo-way/2018/05/22/613250814/president-trump-approves-new-sanctions-on-venezuela?utm_source=twitter.com&utm_medium=social&utm_campaign=politics&utm_term=nprnews&utm_content=20180522"
                },
                {
                    "_id": "5b04771f421aa946f03d1d29",
                    "date_month": "2018-05",
                    "image": "https://twt-thumbs.washtimes.com/media/image/2018/05/21/5_212018_untitled-18201_s1661x2048.jpg?b9027a02ad375e855f4d3aaf8a58543376b8bf21",
                    "origin": "The Washington Times",
                    "title": "Trump disruptions lead to new NATO funding",
                    "ts": 1527015632,
                    "twitterid": 999002087341088770,
                    "url": "https://www.washingtontimes.com/news/2018/may/21/trump-disruptions-lead-to-new-nato-funding/"
                }
            ]
        ]
    },
    {
        "list": [
            92
        ],
        "months": [
            "2018-05"
        ],
        "ne": [
            "Iran",
            "Facebook",
            "Korean",
            "Washington",
            "Trump",
            "Coins As",
            "Happen",
            "Schumer",
            "Rubio",
            "Trump Trump",
            "Trump Warns Summit",
            "Trump Says",
            "Moon",
            "Schedule China",
            "Secret Army",
            "North Korea",
            "Business Trump",
            "Bannon Condemns Mnuchin",
            "Kim Jong Un Trump",
            "ZTE China",
            "China Trade Talks So Far Donald Trump",
            "Mike Pence",
            "China Giveaway",
            "Plot Strategy",
            "ZTE Senate",
            "North",
            "Least",
            "Early Celebration Trump",
            "North Korea Summit",
            "Doubts Republicans",
            "How China",
            "Losses From",
            "U.S.",
            "South",
            "US",
            "White House",
            "ZTE Trump",
            "ZTE Mnuchin Says U.S.",
            "Trump Reconsidering",
            "Korean Nukes",
            "Kim",
            "WATCH",
            "South Korea Fate",
            "Hinder Kim",
            "Senate",
            "Chinese",
            "South Korea",
            "Wilbur Ross",
            "Test Site",
            "U.S. Ban Trump",
            "Donald Trump",
            "Nuke Plans Pessimism",
            "Japan",
            "Coin For North Korea Summit",
            "Come",
            "China",
            "Tariff Risk",
            "ZTE",
            "Trump Says U.S.",
            "ZTE North Korea",
            "ZTE South Korea",
            "USS Milius",
            "Trade Truce",
            "Georgia",
            "Sources Say North Korea",
            "Kim Jong Un",
            "NKorea",
            "South Korean",
            "Pompeo",
            "Russia",
            "Intend",
            "China Tariffs Because of White House Discord",
            "North Korea Trump",
            "Jimmy Carter",
            "Abroad",
            "Kim Could Be",
            "China Trip",
            "ZTE Out",
            "China Trade Truce Inside North Korea",
            "China Trump"
        ],
        "peaks": [],
        "theme": [
            "Trump",
            "summit",
            "China",
            "North",
            "Korea",
            "Kim",
            "ZTE"
        ],
        "timestamp": "2018-05-23 04:11:12.586286-04:00",
        "toparticles": [
            [
                {
                    "_id": "5b04690a421aa946a709a28a",
                    "date_month": "2018-05",
                    "image": "https://www.gannett-cdn.com/-mm-/7f6a882f681a9c11a5473861a77a7f22101141c0/c=0-646-2326-1960&r=x1683&c=3200x1680/local/-/media/2018/05/21/USATODAY/USATODAY/636625193446805040-AP-South-Korea-US-White-House-Talks.jpg",
                    "origin": "USA TODAY",
                    "title": "South Korea's peace hangs on summit with Trump and North's Kim Jong Un",
                    "ts": 1527013204,
                    "twitterid": 998991902182649856,
                    "url": "https://www.usatoday.com/story/news/world/2018/05/22/south-korea-donald-trump-kim-jong-un/630689002/"
                },
                {
                    "_id": "5b045b0f421aa946582afb5b",
                    "date_month": "2018-05",
                    "image": "https://media2.s-nbcnews.com/j/newscms/2018_21/2441031/180522-donald-trump-moon-jae-in-ew-1258p_da63f17b22addcd137721de3ba40d7d2.1200;630;7;70;5.jpg",
                    "origin": "NBC News",
                    "title": "'Substantial chance' summit with North Korea's Kim won't happen in June, Trump says",
                    "ts": 1527011390,
                    "twitterid": 998984292855402497,
                    "url": "https://www.nbcnews.com/politics/donald-trump/substantial-chance-summit-north-korea-s-kim-won-t-happen-n876451"
                },
                {
                    "_id": "5b04771f421aa946f03d1d21",
                    "date_month": "2018-05",
                    "image": "https://media.npr.org/assets/img/2018/05/22/ap_18142606321861_wide-f3f200c0d11049f73d843cdd272d0c46c8a3221d.jpg?s=1400",
                    "origin": "NPR Politics",
                    "title": "Trump Warns Summit With North Korea May Not Happen On Schedule",
                    "ts": 1527015900,
                    "twitterid": 999003210403721216,
                    "url": "https://www.npr.org/2018/05/22/613169662/trump-and-south-korean-president-plot-strategy-on-north-korean-nukes?utm_source=twitter.com&utm_medium=social&utm_campaign=politics&utm_term=nprnews&utm_content=20180522"
                },
                {
                    "_id": "5b044cf5421aa945eda0636a",
                    "date_month": "2018-05",
                    "image": "http://global.fncstatic.com/static/orion/styles/img/fox-news/og/og-fox-news.png",
                    "origin": "Fox News",
                    "title": "Trump suggests historic summit with North Korea could be delayed",
                    "ts": 1527007715,
                    "twitterid": 998968879018803200,
                    "url": "http://www.foxnews.com/politics/2018/05/22/trump-suggests-historic-summit-with-north-korea-could-be-delayed.html"
                },
                {
                    "_id": "5b04af5d421aa9489883f1bb",
                    "date_month": "2018-05",
                    "image": "https://cbsnews1.cbsistatic.com/hub/i/r/2018/04/09/7fa4cb42-dd00-4be6-afef-cf7f43ffa7e6/thumbnail/1200x630/519e0d34eff1711546978ddc9a019370/ap-18099686855661.jpg",
                    "origin": "CBS Evening News",
                    "title": "Trump administration remains vague on future of North Korea summit",
                    "ts": 1527030572,
                    "twitterid": 999064749018112005,
                    "url": "https://www.cbsnews.com/news/live-white-house-briefing-may-22-2018-live-stream/?ftag=CNM-00-10aab8a&linkId=52041151"
                }
            ]
        ]
    },
    {
        "list": [
            97
        ],
        "months": [
            "2018-05"
        ],
        "ne": [
            "Bargain Trump",
            "Stormy Daniels",
            "Huma",
            "Cold",
            "Trump",
            "Jim Himes",
            "Hillary Clinton",
            "Trump Trump",
            "Answered Trump",
            "Mueller",
            "Rosenstein Caputo",
            "FISA",
            "Watch",
            "FBI Trump",
            "DHS",
            "CIA",
            "Stefan Halper",
            "Devil",
            "Justice Department",
            "IG",
            "Justice Dept",
            "GOP",
            "Barack Obama",
            "PhRMA",
            "Does Donald Trump",
            "Impeachable Offenses Just Grew",
            "Badly Chilled Sally",
            "Corker",
            "House",
            "Key",
            "Article II Trump",
            "Congress",
            "City",
            "Trump Web",
            "IRS",
            "Russia Rod Rosenstein",
            "DOJ Mystery",
            "Fears",
            "White House",
            "US",
            "DOJ",
            "Former Trump",
            "Meet Mueller",
            "Choom Gang Ron DeSantis",
            "Trump DOJ",
            "WATCH",
            "Fox",
            "Susan",
            "House Intelligence Committee",
            "Cohen",
            "DOJ House",
            "Donald Trump",
            "Mark Levin",
            "Democrat",
            "Secret Russia Probe Documents",
            "Nixon West Hollywood",
            "Years Will Robert Mueller Need",
            "Australia House",
            "Russian",
            "Russia",
            "Panama",
            "FBI FBI",
            "FBI",
            "Next Manafort"
        ],
        "peaks": [],
        "theme": [
            "Trump",
            "FBI",
            "Probe",
            "campaign",
            "informant",
            "Russia",
            "DOJ"
        ],
        "timestamp": "2018-05-23 04:11:14.450796-04:00",
        "toparticles": [
            [
                {
                    "_id": "5b04149b421aa9444b2ae9db",
                    "date_month": "2018-05",
                    "image": "https://static.politico.com/6a/d5/e6bbb1ab4cc8ac4553c6297836f3/17-donald-trump-128-gty-1160.jpg",
                    "origin": "POLITICO",
                    "title": "DOJ, Trump strike murky deal in FBI informant spat",
                    "ts": 1526994012,
                    "twitterid": 998911404622172165,
                    "url": "https://www.politico.com/story/2018/05/21/trump-justice-department-fbi-informant-601572"
                },
                {
                    "_id": "5b04af5d421aa9489883f1af",
                    "date_month": "2018-05",
                    "image": "https://cbsnews1.cbsistatic.com/hub/i/r/2017/07/17/970e1a0e-b8c2-4c8d-8927-7aae0d75fe0a/thumbnail/1200x630g2/0f55732c686078237400d2b1b5e768da/gettyimages-816523000.jpg",
                    "origin": "CBS Evening News",
                    "title": "Trump fumes over FBI's use of informant during campaign",
                    "ts": 1527031195,
                    "twitterid": 999067359775207424,
                    "url": "https://www.cbsnews.com/news/fbi-informant-2016-campaign-donald-trump-reaction-today-2018-05-22/?ftag=CNM-00-10aab8a&linkId=52041300"
                },
                {
                    "_id": "5b048527421aa9476b5061af",
                    "date_month": "2018-05",
                    "image": "https://static.politico.com/16/aa/971edf2a44928bd45e245ad502ec/180522-schumer-getty-1160.jpg",
                    "origin": "POLITICO",
                    "title": "Democrats not invited to DOJ briefing on FBI informant",
                    "ts": 1527019713,
                    "twitterid": 999019203209424896,
                    "url": "https://www.politico.com/story/2018/05/22/fbi-informant-meeting-doj-gop-democrats-white-house-603275"
                },
                {
                    "_id": "5b04690a421aa946a709a289",
                    "date_month": "2018-05",
                    "image": "https://static.politico.com/47/90/6868884d4e5d9bbc1f5d81957c28/20-donald-trump-23-ap-1160.jpg",
                    "origin": "POLITICO",
                    "title": "Trump says FBI informant in his campaign would be a 'disgrace to this country'",
                    "ts": 1527013211,
                    "twitterid": 998991929575649281,
                    "url": "https://www.politico.com/story/2018/05/22/trump-fbi-informant-disgrace-country-603134"
                },
                {
                    "_id": "5b05119b421aa9532eaca492",
                    "date_month": "2018-05",
                    "image": "https://static.politico.com/47/90/6868884d4e5d9bbc1f5d81957c28/20-donald-trump-23-ap-1160.jpg",
                    "origin": "POLITICO",
                    "title": "Trump says FBI informant in his campaign would be \u2018disgrace to this country\u2019",
                    "ts": 1527055288,
                    "twitterid": 999168414408167425,
                    "url": "https://www.politico.com/story/2018/05/22/trump-fbi-informant-disgrace-country-603134"
                }
            ]
        ]
    }
]